{
  "$schema": "https://developer.microsoft.com/json-schemas/fabric/item/report/definition/visualContainer/2.10.0/schema.json",
  "name": "a7e2425fc25922f982ec",
  "position": {
    "x": 386.04760755702546,
    "y": 161.62836581453774,
    "z": 7000,
    "height": 544.187591375566,
    "width": 345.34981760372455,
    "tabOrder": 7000
  },
  "visual": {
    "visualType": "barChart",
    "query": {
      "queryState": {
        "Category": {
          "projections": [
            {
              "field": {
                "Column": {
                  "Expression": {
                    "SourceRef": {
                      "Entity": "DimTurbines"
                    }
                  },
                  "Property": "TurbineName"
                }
              },
              "queryRef": "DimTurbines.TurbineName",
              "nativeQueryRef": "TurbineName",
              "active": true
            }
          ]
        },
        "Y": {
          "projections": [
            {
              "field": {
                "Aggregation": {
                  "Expression": {
                    "Column": {
                      "Expression": {
                        "SourceRef": {
                          "Entity": "FactProduction"
                        }
                      },
                      "Property": "EnergyProducedMWh"
                    }
                  },
                  "Function": 0
                }
              },
              "queryRef": "Sum(FactProduction.EnergyProducedMWh)",
              "nativeQueryRef": "Sum of EnergyProducedMWh"
            }
          ]
        }
      },
      "sortDefinition": {
        "sort": [
          {
            "field": {
              "Aggregation": {
                "Expression": {
                  "Column": {
                    "Expression": {
                      "SourceRef": {
                        "Entity": "FactProduction"
                      }
                    },
                    "Property": "EnergyProducedMWh"
                  }
                },
                "Function": 0
              }
            },
            "direction": "Descending"
          }
        ],
        "isDefaultSort": true
      }
    },
    "drillFilterOtherVisuals": true
  }
}